{"yflhvMFJ//Gncc19l8RWng==":"mbr-1.jpg","T4zkQrDWb0m9qIv27c5rVg==":"mbr-2.jpg","Z0s7uTFMjKcQ7ngLc5lmnA==":"mbr.jpg","wzidloMrha3tuSON+OV1Cw==":"mbr-3.jpg","FhC12xVKkvIETQMVKu9WsA==":"mbr-4.jpg","XLOa+k8BKjlTYw4d/uEulQ==":"mbr-6.jpg","LAL131GPhuSNnoifNS/NrQ==":"mbr.jpeg","n3xLfiICRwBK7qZAxZQ4ig==":"mbr-6.jpeg","61tx7eiw/R1KSuuIhkCgyw==":"mbr-4.jpeg","7BusHJYMZF5vA0Q1cmlFTQ==":"mbr-9.jpeg","YRJAA6ew0xAs6F0Ax5Rfvw==":"mbr-11.jpeg","DUgaHyV9oTcz7ZCUxJbpSQ==":"mbr-2.jpeg","nmaFfquSo95VQKE0s/iKhQ==":"mbr-3.jpeg","fdrkojhpw03cB3GSjvgDuw==":"mbr-12.jpeg","Gjo+fRcaTLdlEzWBcy0xQw==":"mbr-5.jpg","lNz+1WZ+Jsut4WEwqonaVg==":"mbr-7.jpg","r4SJW6vvdWfNTKjQSApHUw==":"mbr-8.jpg","aj6nI9PXScsDr4XezM2cNg==":"mbr-9.jpg","l3O6KHUARGL95+Th0X0BuQ==":"mbr-10.jpg","lK77ih7fT22RGPy5YZlknA==":"mbr-10.jpeg","9MA44v7wAXZf/YRNZxJK9Q==":"mbr-13.jpeg","uUTtwDNVtKLOj7cIFnet6w==":"mbr-14.jpeg","Q6iFla8InJcXTnXwrhQJBw==":"mbr-15.jpeg","r2I82yeII6avCvXJVP6Hhg==":"mbr-16.jpeg","/HVusEn4Av1iT9/R8YDOAA==":"mbr-11.jpg","CRxHHjX0jfgqDfEHqFpEbQ==":"mbr-17.jpeg","nZ522L3IHqZbQdLdB4urcw==":"mbr-18.jpeg","FUFWlmEDrx/Wq7juCg4sdQ==":"mbr-19.jpeg","kgPc6Z3mClKN6Ps+h/pg/Q==":"mbr-20.jpeg","LqGAA2b4ffmyh+obQSOzpQ==":"logo-sbsi.jpeg-80x76.jpeg","EtUmsALwQxWtz30RFzuvrQ==":"logo-sbsi.jpeg-1-80x76.jpeg","23CDStezzTo6F9qnLhDeDw==":"logo-sbsi-1.png-102x19.png","Wmk7Tork6fClXpYlGdP8iw==":"sbsi-logo-2-1x.png-540x235.png","xOCMMJns7B1hQk215I6F8A==":"kota-dobo-kepulauan-aru2.jpg-1280x576.jpeg","HLV0Ol/qZQ8vrnS5VR9sJQ==":"kota-dobo-kepulauan-aru2.jpg-1-1280x576.jpeg","9pomVlc/C3Wzq2ORr77L1w==":"mbr-2.jpg","3lP1Ms5Ha9D8lbNyDYiLzw==":"whatsapp-image-2020-12-03-at-23.19.25.jpeg-651x527.jpg","hvxIYJbHmr3+Fqg1rCxUZQ==":"mbr-1256x829.jpg","LfnZkJJL/JyyM2mNputudQ==":"ksbsi.jpg-264x264.jpeg","s/jN/NwoCVCHzMZHD2bSEQ==":"ksbsi.jpg-285x285.jpeg","3Jrw2ElSvNAfBEpHuv60SA==":"ksbsi.jpg-446x446.jpeg","8vfm89V8YquesYRnt9FW+Q==":"ksbsi-logo-kanan-web.jpg-458x458.jpeg","+CaotRBnVcVMNyGUOqawRg==":"karel-ridolof-labok.jpg-1076x1522.jpeg","704PCW8I2KYL6E+ujeGZ+Q==":"karel-ridolof-labok.jpg-1587x2245.jpeg","MLhFJpsMsYsQ1h0SEGLc7A==":"281716800048.jpg-740x416.jpeg","1kkPnEEIvQyYcd/eOioSPQ==":"861746276203.jpg-1200x675.jpg","efOwD8V85C6rr16RErYjeQ==":"861746276203.jpg-695x391.jpeg","oXruzR7cFt1IlgyKZPxgkg==":"581746164715.jpg-695x392.jpeg","U6b7M4SuMJNlPNgYN3VeKQ==":"601746015362.jpg-695x391.jpeg","Rm5LE+0duLn4zsXm/tsYvw==":"531740659694.jpg-740x416.jpeg","/2yvZZdMyNU8ULre0NZngg==":"601746015362.jpg-740x416.jpg","oUP3ojyr0IqR0fvlE6Tg7Q==":"fb-img-1696631600196.jpg-569x678.jpg","adFbo5mGkeDiqi4cGBO5Mg==":"fb-img-1696631600196.jpg-569x678.jpeg","+G7bgA4fG0+TsSRWvvYBeg==":"fb-img-1696631600196.jpg-1-569x678.jpeg","DWPH/Y48/eqjqWSSX91PAA==":"img-20230426-135356.jpg-444x283.jpeg","jGpm2oflYAaMafN6npv12Q==":"yun.jpg-644x396.jpeg","fenxRV0YpzxpkRDAZ1/gdA==":"ksbsi-logo-kanan-web.jpg-500x500.jpeg","bSoF3RZYh+sfW+kuu0nhZw==":"ksbsi-logo-kanan-web.jpg-1-500x500.jpeg","TmYcGGrFLNvna05Xk2Dpiw==":"ksbsi-logo-kanan-web.jpg-2-500x500.jpeg","Z5f+KOnA+WBWVNpwZ9OLxQ==":"ksbsi.jpg-500x500.jpeg","j99xsqvinZYEjl3dwFWYGA==":"struktur-organisasi.jpg-1587x2245.jpeg","I9PwDuN4KAEMKM1q5fs2JQ==":"ksbsi-logo-kanan-web.jpg-500x500.jpg","Jf+4lVme79vWHKTP6xum5w==":"whatsapp-image-2020-12-03-at-23.19.25.jpeg-600x486.jpg","v/dnvkH/xH5n61Z9pUfb3w==":"sbsi-1.jpg-600x337.jpg","67TVft1vEfG9QbSFVt4XMw==":"sbsi-1.jpg-600x337.jpeg","5jMaD6u2jmf9qUM4hb7Vdw==":"rusdy-panca.jpg-600x337.jpeg","6B9Aq1npt33zYOnrdxg7UQ==":"sbsi-hak.jpg-600x337.jpeg","XuXifbFWDVk2ulBkobmZ1w==":"background5.jpeg","M2DsebZzJQtGgI1IFIX+jA==":"screenshot%25202025-05-25%2520030724-609x865.jpg","j6D9RJ/s++VG+3Qq05EWtw==":"2-595x873.jpeg","mObPXG3m3B2EQ2xBwnSHOQ==":"3-607x858.jpg","jsLFqJ5IpLQCPQjn4rArfg==":"4-661x690.jpeg","XAugA3LqfPibyLcloWIzZw==":"kota-dobo-kepulauan-aru2.jpg-2-1280x576.jpeg","k3jhSo8sbVg0xutUmyjnfw==":"kota-dobo-kepulauan-aru2-1-1280x576.jpeg","ZyH7kBb7AYg1nk4Mp8NFTQ==":"maxresdefault-1280x720.jpeg","sjm9N4gv/bgdtFgqoTTz8g==":"maxresdefault-1-1280x720.jpeg","LMMJa4QWmQINnPS039OZwQ==":"maxresdefault-2-1280x720.jpeg","JEyLEeUze8iPMn3lC87CTA==":"kota-dobo-kepulauan-aru2-2-1280x576.jpeg","PPITbkd6ZUqSJp/wBgYBTw==":"maxresdefault-3-1280x720.jpeg","eaToLVpa8jFO2+Aa/BhEiw==":"kota-dobo-kepulauan-aru2-3-1280x576.jpeg","hNhDY5CxjraORVX97kYt+A==":"kota-dobo-kepulauan-aru2-4-1280x576.jpeg","OodQ3oIZCrRcAfGoI1fSEw==":"maxresdefault-4-1280x720.jpeg","ZukycEjBtftKOpwvkt2Mig==":"ksbsi-500x500.jpeg","SFt6PRhCjWz5seJfa2HtJw==":"ksbsi%2520logo%2520kanan%2520web-500x500.jpeg","I9rUK7FSTcNX7U/ZcadnXg==":"oad-204x192.png","IotabchK4bOtl3x3GGFB5g==":"logo_unriyo_baru-188x188.png","jLkt7VgahNh7T/c7i75ZeA==":"logo_unriyo_baru-337x337.png","JvGGaa63ZKbfqjSW4cxqbA==":"kota-dobo-kepulauan-aru2-5-1280x576.jpeg","ksxoe0auOcHhoCNsk8dD0g==":"kota-dobo-kepulauan-aru2-6-1280x576.jpeg","bZixGGRFWR4MyxsqqGRJAQ==":"maxresdefault-5-1280x720.jpeg","YvQnYxqo/bPm/c3+OgwYEw==":"maxresdefault-6-1280x720.jpeg","GQQg2Mc74jlMtFInZ+yy3Q==":"maxresdefault-7-1280x720.jpeg","9lmLTtLk+TAMgGq+AAjk+A==":"img-20250414-wa0009-600x800.jpeg","+eGhCQqZDRcZZ66KFLgmrQ==":"img-20250414-wa0006-600x841.jpeg","/zWDwQ3BlcxaWuhnR/3vQQ==":"img-20250414-wa0013-600x946.jpeg","tW2lFy42BjBUzcMI6mx1rQ==":"img-20250414-wa0008-600x800.jpeg","F4ychxGqkeX6Oi+dja2yXA==":"img-20250414-wa0010-600x800.jpg","fD6jGAwkot3gqa24GxkXLg==":"img-20250414-wa0010-960x1280.jpeg","ur7JFRZi42EKprPGgBCKiw==":"img-20250414-wa0005-452x552.jpg","WsM3YqiVpFkqD3PucVz5ww==":"img-20250414-wa0012-513x668.jpg","yQgepNa/OEGUx/+J52gsvg==":"img-20250414-wa0007-331x449.jpg","b88WqMsovaLiw6JOUi1J3w==":"img-20250414-wa0015-331x497.jpg","VyU80kfZn9F+FwYoFl8CiA==":"img-20250414-wa0011-331x441.jpg","DyR9vgovYwf2avTpQA0Gew==":"img-20250414-wa0014-331x441.jpg","QVCBj+RtM2nUq15yxqIXEw==":"kapolda-ntt-1746154383200-169-506x285.jpg","IR0yBwQvpMHTNEkQ8SEJog==":"kapolda-ntt-1746154383200-169-700x394.jpg","AQGePzPpPZZdyWqJENkRfQ==":"pelipus-taurwewar-700x393.jpg","mZ9cr6i7iyBKee13B/VWyA==":"18102023-direktur-pd-panca-karya-700x393.jpg","88EnGoNVAC9ve133+3laCQ==":"ksbsi%2520logo%2520kanan%2520web-500x500.jpeg","YeXMjxxZrjgWHAgV0w8JcA==":"maxresdefault-1280x720.jpg","1GR52+vnEGq1zV1/QWcr7Q==":"kota-dobo-kepulauan-aru2-1-1280x576.jpg","sVvKVVDZ2wfnfIHp9w4ZVA==":"screenshot%25202025-05-25%2520030724-609x865.jpeg","fQDu0pfMNAtJsTn+wk6o/A==":"3-607x858.jpeg","yRDqZfsm06sdJqLFZUdYiA==":"4-607x634.jpg","Vb7GgbMoe0curpGYBParsg==":"background3.jpg","n1dx+NZv3qks526xC0hZ5Q==":"background13.jpg"}